{
  "id": "773aca7d-6454-4d89-83e4-13663f9cda17",
  "prevId": "00000000-0000-0000-0000-000000000000",
  "version": "7",
  "dialect": "postgresql",
  "tables": {
    "public.banners": {
      "name": "banners",
      "schema": "",
      "columns": {
        "id": {
          "name": "id",
          "type": "serial",
          "primaryKey": true,
          "notNull": true
        },
        "titulo": {
          "name": "titulo",
          "type": "text",
          "primaryKey": false,
          "notNull": true
        },
        "subtitulo": {
          "name": "subtitulo",
          "type": "text",
          "primaryKey": false,
          "notNull": false
        },
        "color": {
          "name": "color",
          "type": "text",
          "primaryKey": false,
          "notNull": false,
          "default": "'brand'"
        },
        "link": {
          "name": "link",
          "type": "text",
          "primaryKey": false,
          "notNull": false
        },
        "activo": {
          "name": "activo",
          "type": "boolean",
          "primaryKey": false,
          "notNull": true,
          "default": true
        }
      },
      "indexes": {},
      "foreignKeys": {},
      "compositePrimaryKeys": {},
      "uniqueConstraints": {},
      "policies": {},
      "checkConstraints": {},
      "isRLSEnabled": false
    },
    "public.barrios": {
      "name": "barrios",
      "schema": "",
      "columns": {
        "id": {
          "name": "id",
          "type": "serial",
          "primaryKey": true,
          "notNull": true
        },
        "nombre": {
          "name": "nombre",
          "type": "text",
          "primaryKey": false,
          "notNull": true
        },
        "ciudad_id": {
          "name": "ciudad_id",
          "type": "integer",
          "primaryKey": false,
          "notNull": true
        },
        "x": {
          "name": "x",
          "type": "real",
          "primaryKey": false,
          "notNull": true
        },
        "y": {
          "name": "y",
          "type": "real",
          "primaryKey": false,
          "notNull": true
        },
        "precio_mes_anterior": {
          "name": "precio_mes_anterior",
          "type": "integer",
          "primaryKey": false,
          "notNull": true,
          "default": 0
        }
      },
      "indexes": {},
      "foreignKeys": {
        "barrios_ciudad_id_ciudades_id_fk": {
          "name": "barrios_ciudad_id_ciudades_id_fk",
          "tableFrom": "barrios",
          "tableTo": "ciudades",
          "columnsFrom": [
            "ciudad_id"
          ],
          "columnsTo": [
            "id"
          ],
          "onDelete": "no action",
          "onUpdate": "no action"
        }
      },
      "compositePrimaryKeys": {},
      "uniqueConstraints": {},
      "policies": {},
      "checkConstraints": {},
      "isRLSEnabled": false
    },
    "public.ciudades": {
      "name": "ciudades",
      "schema": "",
      "columns": {
        "id": {
          "name": "id",
          "type": "serial",
          "primaryKey": true,
          "notNull": true
        },
        "nombre": {
          "name": "nombre",
          "type": "text",
          "primaryKey": false,
          "notNull": true
        },
        "provincia": {
          "name": "provincia",
          "type": "text",
          "primaryKey": false,
          "notNull": true,
          "default": "'Córdoba'"
        },
        "slug": {
          "name": "slug",
          "type": "text",
          "primaryKey": false,
          "notNull": true
        },
        "activa": {
          "name": "activa",
          "type": "boolean",
          "primaryKey": false,
          "notNull": true,
          "default": true
        },
        "created_at": {
          "name": "created_at",
          "type": "timestamp",
          "primaryKey": false,
          "notNull": false,
          "default": "now()"
        }
      },
      "indexes": {},
      "foreignKeys": {},
      "compositePrimaryKeys": {},
      "uniqueConstraints": {
        "ciudades_slug_unique": {
          "name": "ciudades_slug_unique",
          "nullsNotDistinct": false,
          "columns": [
            "slug"
          ]
        }
      },
      "policies": {},
      "checkConstraints": {},
      "isRLSEnabled": false
    },
    "public.password_reset_tokens": {
      "name": "password_reset_tokens",
      "schema": "",
      "columns": {
        "id": {
          "name": "id",
          "type": "serial",
          "primaryKey": true,
          "notNull": true
        },
        "user_id": {
          "name": "user_id",
          "type": "integer",
          "primaryKey": false,
          "notNull": true
        },
        "token": {
          "name": "token",
          "type": "text",
          "primaryKey": false,
          "notNull": true
        },
        "expires_at": {
          "name": "expires_at",
          "type": "timestamp",
          "primaryKey": false,
          "notNull": true
        },
        "used": {
          "name": "used",
          "type": "boolean",
          "primaryKey": false,
          "notNull": true,
          "default": false
        },
        "created_at": {
          "name": "created_at",
          "type": "timestamp",
          "primaryKey": false,
          "notNull": false,
          "default": "now()"
        }
      },
      "indexes": {},
      "foreignKeys": {
        "password_reset_tokens_user_id_users_id_fk": {
          "name": "password_reset_tokens_user_id_users_id_fk",
          "tableFrom": "password_reset_tokens",
          "tableTo": "users",
          "columnsFrom": [
            "user_id"
          ],
          "columnsTo": [
            "id"
          ],
          "onDelete": "cascade",
          "onUpdate": "no action"
        }
      },
      "compositePrimaryKeys": {},
      "uniqueConstraints": {
        "password_reset_tokens_token_unique": {
          "name": "password_reset_tokens_token_unique",
          "nullsNotDistinct": false,
          "columns": [
            "token"
          ]
        }
      },
      "policies": {},
      "checkConstraints": {},
      "isRLSEnabled": false
    },
    "public.profesionales": {
      "name": "profesionales",
      "schema": "",
      "columns": {
        "id": {
          "name": "id",
          "type": "serial",
          "primaryKey": true,
          "notNull": true
        },
        "nombre": {
          "name": "nombre",
          "type": "text",
          "primaryKey": false,
          "notNull": true
        },
        "rol": {
          "name": "rol",
          "type": "text",
          "primaryKey": false,
          "notNull": true
        },
        "matricula": {
          "name": "matricula",
          "type": "text",
          "primaryKey": false,
          "notNull": false
        },
        "rating": {
          "name": "rating",
          "type": "real",
          "primaryKey": false,
          "notNull": false,
          "default": 5
        },
        "iniciales": {
          "name": "iniciales",
          "type": "text",
          "primaryKey": false,
          "notNull": true
        },
        "color": {
          "name": "color",
          "type": "text",
          "primaryKey": false,
          "notNull": false,
          "default": "'brand'"
        },
        "telefono": {
          "name": "telefono",
          "type": "text",
          "primaryKey": false,
          "notNull": false
        },
        "email": {
          "name": "email",
          "type": "text",
          "primaryKey": false,
          "notNull": false
        }
      },
      "indexes": {},
      "foreignKeys": {},
      "compositePrimaryKeys": {},
      "uniqueConstraints": {},
      "policies": {},
      "checkConstraints": {},
      "isRLSEnabled": false
    },
    "public.properties": {
      "name": "properties",
      "schema": "",
      "columns": {
        "id": {
          "name": "id",
          "type": "serial",
          "primaryKey": true,
          "notNull": true
        },
        "user_id": {
          "name": "user_id",
          "type": "integer",
          "primaryKey": false,
          "notNull": true
        },
        "ciudad_id": {
          "name": "ciudad_id",
          "type": "integer",
          "primaryKey": false,
          "notNull": true
        },
        "titulo": {
          "name": "titulo",
          "type": "text",
          "primaryKey": false,
          "notNull": true
        },
        "tipo": {
          "name": "tipo",
          "type": "text",
          "primaryKey": false,
          "notNull": true
        },
        "direccion": {
          "name": "direccion",
          "type": "text",
          "primaryKey": false,
          "notNull": true
        },
        "barrio": {
          "name": "barrio",
          "type": "text",
          "primaryKey": false,
          "notNull": true
        },
        "precio": {
          "name": "precio",
          "type": "integer",
          "primaryKey": false,
          "notNull": true
        },
        "precio_anterior": {
          "name": "precio_anterior",
          "type": "integer",
          "primaryKey": false,
          "notNull": false
        },
        "ambientes": {
          "name": "ambientes",
          "type": "integer",
          "primaryKey": false,
          "notNull": true,
          "default": 1
        },
        "banos": {
          "name": "banos",
          "type": "integer",
          "primaryKey": false,
          "notNull": true,
          "default": 1
        },
        "superficie": {
          "name": "superficie",
          "type": "integer",
          "primaryKey": false,
          "notNull": true,
          "default": 0
        },
        "garantia": {
          "name": "garantia",
          "type": "garantia",
          "typeSchema": "public",
          "primaryKey": false,
          "notNull": true,
          "default": "'requerida'"
        },
        "mascotas": {
          "name": "mascotas",
          "type": "boolean",
          "primaryKey": false,
          "notNull": true,
          "default": false
        },
        "amoblado": {
          "name": "amoblado",
          "type": "boolean",
          "primaryKey": false,
          "notNull": true,
          "default": false
        },
        "expensas_incluidas": {
          "name": "expensas_incluidas",
          "type": "boolean",
          "primaryKey": false,
          "notNull": true,
          "default": false
        },
        "destacado": {
          "name": "destacado",
          "type": "boolean",
          "primaryKey": false,
          "notNull": true,
          "default": false
        },
        "liquidacion": {
          "name": "liquidacion",
          "type": "boolean",
          "primaryKey": false,
          "notNull": true,
          "default": false
        },
        "descripcion": {
          "name": "descripcion",
          "type": "text",
          "primaryKey": false,
          "notNull": false
        },
        "imagen": {
          "name": "imagen",
          "type": "text",
          "primaryKey": false,
          "notNull": false
        },
        "created_at": {
          "name": "created_at",
          "type": "timestamp",
          "primaryKey": false,
          "notNull": false,
          "default": "now()"
        }
      },
      "indexes": {
        "idx_properties_ciudad_id": {
          "name": "idx_properties_ciudad_id",
          "columns": [
            {
              "expression": "ciudad_id",
              "isExpression": false,
              "asc": true,
              "nulls": "last"
            }
          ],
          "isUnique": false,
          "concurrently": false,
          "method": "btree",
          "with": {}
        },
        "idx_properties_tipo": {
          "name": "idx_properties_tipo",
          "columns": [
            {
              "expression": "tipo",
              "isExpression": false,
              "asc": true,
              "nulls": "last"
            }
          ],
          "isUnique": false,
          "concurrently": false,
          "method": "btree",
          "with": {}
        },
        "idx_properties_barrio": {
          "name": "idx_properties_barrio",
          "columns": [
            {
              "expression": "barrio",
              "isExpression": false,
              "asc": true,
              "nulls": "last"
            }
          ],
          "isUnique": false,
          "concurrently": false,
          "method": "btree",
          "with": {}
        },
        "idx_properties_precio": {
          "name": "idx_properties_precio",
          "columns": [
            {
              "expression": "precio",
              "isExpression": false,
              "asc": true,
              "nulls": "last"
            }
          ],
          "isUnique": false,
          "concurrently": false,
          "method": "btree",
          "with": {}
        },
        "idx_properties_created_at": {
          "name": "idx_properties_created_at",
          "columns": [
            {
              "expression": "created_at",
              "isExpression": false,
              "asc": true,
              "nulls": "last"
            }
          ],
          "isUnique": false,
          "concurrently": false,
          "method": "btree",
          "with": {}
        },
        "idx_properties_user_id": {
          "name": "idx_properties_user_id",
          "columns": [
            {
              "expression": "user_id",
              "isExpression": false,
              "asc": true,
              "nulls": "last"
            }
          ],
          "isUnique": false,
          "concurrently": false,
          "method": "btree",
          "with": {}
        }
      },
      "foreignKeys": {
        "properties_user_id_users_id_fk": {
          "name": "properties_user_id_users_id_fk",
          "tableFrom": "properties",
          "tableTo": "users",
          "columnsFrom": [
            "user_id"
          ],
          "columnsTo": [
            "id"
          ],
          "onDelete": "cascade",
          "onUpdate": "no action"
        },
        "properties_ciudad_id_ciudades_id_fk": {
          "name": "properties_ciudad_id_ciudades_id_fk",
          "tableFrom": "properties",
          "tableTo": "ciudades",
          "columnsFrom": [
            "ciudad_id"
          ],
          "columnsTo": [
            "id"
          ],
          "onDelete": "no action",
          "onUpdate": "no action"
        }
      },
      "compositePrimaryKeys": {},
      "uniqueConstraints": {},
      "policies": {},
      "checkConstraints": {},
      "isRLSEnabled": false
    },
    "public.users": {
      "name": "users",
      "schema": "",
      "columns": {
        "id": {
          "name": "id",
          "type": "serial",
          "primaryKey": true,
          "notNull": true
        },
        "nombre": {
          "name": "nombre",
          "type": "text",
          "primaryKey": false,
          "notNull": true
        },
        "email": {
          "name": "email",
          "type": "text",
          "primaryKey": false,
          "notNull": true
        },
        "password_hash": {
          "name": "password_hash",
          "type": "text",
          "primaryKey": false,
          "notNull": true
        },
        "rol": {
          "name": "rol",
          "type": "rol",
          "typeSchema": "public",
          "primaryKey": false,
          "notNull": true,
          "default": "'usuario'"
        },
        "empresa": {
          "name": "empresa",
          "type": "text",
          "primaryKey": false,
          "notNull": false
        },
        "telefono": {
          "name": "telefono",
          "type": "text",
          "primaryKey": false,
          "notNull": false
        },
        "created_at": {
          "name": "created_at",
          "type": "timestamp",
          "primaryKey": false,
          "notNull": false,
          "default": "now()"
        }
      },
      "indexes": {},
      "foreignKeys": {},
      "compositePrimaryKeys": {},
      "uniqueConstraints": {
        "users_email_unique": {
          "name": "users_email_unique",
          "nullsNotDistinct": false,
          "columns": [
            "email"
          ]
        }
      },
      "policies": {},
      "checkConstraints": {},
      "isRLSEnabled": false
    }
  },
  "enums": {
    "public.garantia": {
      "name": "garantia",
      "schema": "public",
      "values": [
        "requerida",
        "sin",
        "ambas"
      ]
    },
    "public.rol": {
      "name": "rol",
      "schema": "public",
      "values": [
        "admin",
        "inmobiliaria",
        "usuario"
      ]
    }
  },
  "schemas": {},
  "sequences": {},
  "roles": {},
  "policies": {},
  "views": {},
  "_meta": {
    "columns": {},
    "schemas": {},
    "tables": {}
  }
}